Metadata-Version: 1.2
Name: py-code
Version: 0.0.3
Summary: Script to generate boilerplate code
Home-page: UNKNOWN
Author: Anh Tong
Author-email: somebody@somewhere.com
License: UNKNOWN
Platform: UNKNOWN
Requires-Python: >=3.6
